aiearth/core/__init__.py
aiearth/core/auth.py
aiearth/core/env.py
aiearth/core/g_var.py
aiearth/core/client/__init__.py
aiearth/core/client/client.py
aiearth/core/client/constants.py
aiearth/core/client/endpoints.py
aiearth/core/error/__init__.py
aiearth/core/error/aie_error.py
aiearth_core-1.0.3.dist-info/LICENSE
aiearth_core-1.0.3.dist-info/METADATA
aiearth_core-1.0.3.dist-info/WHEEL
aiearth_core-1.0.3.dist-info/top_level.txt
aiearth_core-1.0.3.dist-info/RECORD
