Metadata-Version: 2.1
Name: aiearth-core
Version: 1.0.3
Summary: AIEarth Engine Python SDK Core
Home-page: https://engine-aiearth.aliyun.com/
Author: AI Earth developer team
Author-email: aiearth@service.aliyun.com
License: APACHE LICENSE, VERSION 2.0
Requires-Python: >=3.8.0
License-File: LICENSE
Requires-Dist: alibabacloud-aiearth-engine20220609 (>=1.0.5)
Requires-Dist: watchdog (~=2.1.6)
